LICENSE
README.md
setup.py
pd4anal/__init__.py
pd4anal/utils.py
pd4anal.egg-info/PKG-INFO
pd4anal.egg-info/SOURCES.txt
pd4anal.egg-info/dependency_links.txt
pd4anal.egg-info/top_level.txt
pd4anal/data/__init__.py
pd4anal/data/frame.py
pd4anal/data/schema.py
pd4anal/data/series.py
pd4anal/dataloader/__init__.py
pd4anal/dataloader/base.py
pd4anal/dataloader/common_fund_data.py
pd4anal/dataloader/common_user_behavior_1000.py
pd4anal/dataloader/common_user_behavior_128.py
pd4anal/dataloader/common_user_behavior_15.py
pd4anal/dataloader/common_user_bic.py
pd4anal/dataloader/common_user_bic_reg_behavior.py
pd4anal/dataloader/common_user_invest_product.py
pd4anal/dataloader/common_user_reg_info.py
pd4anal/dataloader/common_user_tel_wetalk_wechat.py
pd4anal/dataloader/scene_novalid2valid_data.py
pd4anal/dataloader/scene_user_fund_data.py
pd4anal/evaluator/__init__.py
pd4anal/evaluator/feature_importance.py
pd4anal/evaluator/metrics.py
pd4anal/models/__init__.py
pd4anal/models/base.py
pd4anal/models/ge_matrix.py
pd4anal/models/model_center.py
pd4anal/models/xgboost.py
pd4anal/pipline/__init__.py
pd4anal/pipline/pipeline.py
pd4anal/preprocessing/__init__.py
pd4anal/preprocessing/data_split.py
pd4anal/preprocessing/feature_selection/__init__.py
pd4anal/preprocessing/feature_selection/corrlation_select.py
pd4anal/preprocessing/feature_selection/entropy_select.py
pd4anal/preprocessing/feature_selection/iv_select.py
pd4anal/preprocessing/feature_selection/monotonicity_select.py
pd4anal/preprocessing/feature_selection/nan_select.py
pd4anal/preprocessing/feature_selection/variance_select.py
pd4anal/preprocessing/feature_transform/__init__.py
pd4anal/preprocessing/feature_transform/custom_transform.py
pd4anal/preprocessing/feature_transform/default_transform.py
pd4anal/preprocessing/feature_transform/dense_transform.py
pd4anal/preprocessing/feature_transform/feature_transform_flow.py
pd4anal/preprocessing/feature_transform/nan_transform.py
pd4anal/preprocessing/feature_transform/sparse_transform.py
pd4anal/preprocessing/feature_transform/tranform_center.py
