Metadata-Version: 2.1
Name: pd4anal
Version: 0.0.1
Summary: an elegant pd4nanl
Home-page: https://github.com/Tongjilibo/pd4anal
Author: Tongjilibo
License: MIT Licence
License-File: LICENSE
